{
  "skill_path": "bilibili-youtube-watcher",
  "files_scanned": 4,
  "findings": [
    {
      "level": "MEDIUM",
      "category": "network_request",
      "description": "urllib usage",
      "file": "get_transcript.py",
      "line": 13,
      "snippet": "sys import tempfile from pathlib import Path from urllib.parse import urlparse  def detect_platform(",
      "confidence": 0.8
    }
  ],
  "risk_summary": {
    "HIGH": 0,
    "MEDIUM": 1,
    "LOW": 0,
    "INFO": 0
  },
  "security_assessment": "🟢 CAUTION: Some medium-risk issues found. Review suggested.",
  "scan_time": 0.03223824501037598,
  "timestamp": "2026-02-21T13:35:42.116148"
}
